Metadata-Version: 2.1
Name: dynamic-plt
Version: 0.0.2
Author: 菜鸟东
